setup.py
powerline_docker/__init__.py
powerline_docker/segments.py
powerline_docker.egg-info/PKG-INFO
powerline_docker.egg-info/SOURCES.txt
powerline_docker.egg-info/dependency_links.txt
powerline_docker.egg-info/requires.txt
powerline_docker.egg-info/top_level.txt