Metadata-Version: 1.1
Name: powerline-docker
Version: 1.0.3
Summary: A Powerline segment for showing Docker container statuses
Home-page: https://github.com/adrianmo/powerline-docker
Author: Adrian Moreno Martinez
Author-email: adrian@morenomartinez.com
License: MIT
Keywords: powerline docker container status
Platform: UNKNOWN
Classifier: Environment :: Console
Classifier: Intended Audience :: Developers
Classifier: License :: OSI Approved :: MIT License
Classifier: Topic :: Terminals
